photosync/__init__.py
photosync/photosync.py
photosync-1.0.0.dist-info/entry_points.txt
photosync-1.0.0.dist-info/LICENSE
photosync-1.0.0.dist-info/WHEEL
photosync-1.0.0.dist-info/METADATA
photosync-1.0.0.dist-info/RECORD
