Metadata-Version: 2.1
Name: photosync
Version: 1.0.0
Summary: Synchronize your phone photos easily
Home-page: https://github.com/bravefencermusashi/photosync
License: GPL-3.0
Author: Alexandre G
Author-email: alex.git@ralouf.fr
Requires-Python: >=3.8,<4.0
Classifier: Environment :: Console
Classifier: License :: OSI Approved :: GNU General Public License v3 (GPLv3)
Classifier: Operating System :: OS Independent
Classifier: Programming Language :: Python :: 3
Classifier: Programming Language :: Python :: 3.8
Classifier: Topic :: Software Development :: Libraries :: Python Modules
Project-URL: Repository, https://github.com/bravefencermusashi/photosync
